{
    "deliveryAddress": "",
    "bottomBar": [
        {
            "image": "",
            "title": "首页",
            "link": "https://m.mogu.com?acm=3.mce.1_10_1jiuu.127180.0.gjcZisJEPcDLP.pos_0-m_455423-sd_119",
            "selected": ""
        },
        {
            "selected": "",
            "image": "",
            "title": "商城",
            "link": "https://act.mogu.com/mmall?acm=3.mce.1_10_1jiuw.127180.0.gjcZisJEPcDLQ.pos_1-m_455424-sd_119"
        },
        {
            "title": "直播",
            "link": "https://h5.mogu.com/live-mona/live-list.html?acm=3.mce.1_10_1jiuy.127180.0.gjcZisJEPcDLR.pos_2-m_455425-sd_119",
            "selected": "",
            "image": ""
        },
        {
            "title": "我",
            "link": "https://h5.mogu.com/personal-v2/index.html?acm=3.mce.1_10_1jiv0.127180.0.gjcZisJEPcDLS.pos_3-m_455426-sd_119",
            "selected": "",
            "image": ""
        }
    ],
    "homeProfile": {
        "cFans": 0,
        "nativeMemberJumpUrl": "https://act.mogu.com/huiyuanzhongxin",
        "personalJumpUrl": "https://h5.mogu.com/brand-content/personal-homepage.html?uid=1fn2gn0",
        "identityIcon": "",
        "userName": "m_170bjg4t7m9vg",
        "cFollow": 0,
        "backgroundImage": "https://s10.mogucdn.com/mlcdn/c45406/190905_24h88agd7ba4a0kl8b530gid6433g_1125x1308.png",
        "memberBannerImage": "https://s10.mogucdn.com/mlcdn/c45406/191010_2il1l3i91gkd5c461j93e5ehfcgi5_1404x216.png",
        "userInfoJumpUrl": "mgj://userinfo",
        "showMedal": false,
        "memberCenterIcon": "https://s10.mogucdn.com/mlcdn/c45406/190627_1i49i2a2cj6fll5bh25l07d53l008_72x72.png",
        "memberCenterJumpUrl": "https://act.mogu.com/huiyuanzhongxin",
        "brandNum": 0,
        "avatarUrl": "http://s11.mogucdn.com/new1/v1/bdefaultavatar/02.jpg_160x160.jpg",
        "lookNum": 0
    },
    "blockInfo": [
        {
            "layoutType": "0",
            "itemListInfo": [
                {
                    "title": "我的主页",
                    "subTitle": "",
                    "jumpUrl": "https://h5.mogu.com/brand-content/personal-homepage.html?uid=1fn2gn0&acm=3.mce.1_10_1m5di.139413.0.uXJuTsJEPd0Y2.pos_9900-m_516671-sd_119",
                    "widgetId": 10,
                    "needExpose": true,
                    "iconUrl": "https://s10.mogucdn.com/mlcdn/c45406/190815_7a9da7lh4a96lb1fl6b4gb854f3ji_75x75.png"
                },
                {
                    "title": "消息",
                    "subTitle": "",
                    "jumpUrl": "http://www.mogu.com/x/im?imver=1.2&show_header=qq#recent&acm=3.mce.1_10_1m5dk.139413.0.uXJuTsJEPd0Y3.pos_9901-m_516672-sd_119",
                    "widgetId": 100,
                    "needExpose": true,
                    "iconUrl": "https://s10.mogucdn.com/mlcdn/c45406/190815_6f41b17399aha0flla6chjb0lhk47_75x75.png"
                },
                {
                    "title": "收藏",
                    "subTitle": "",
                    "jumpUrl": "http://h5.mogu.com/fav/list.html?type=goods&acm=3.mce.1_10_1m5dm.139413.0.uXJuTsJEPd0Y4.pos_9902-m_516673-sd_119",
                    "widgetId": 101,
                    "needExpose": true,
                    "iconUrl": "https://s10.mogucdn.com/mlcdn/c45406/190815_31g4a5ebc8bj2f85cj4li8df89aab_75x75.png"
                },
                {
                    "jumpUrl": "https://h5.mogu.com/brand-content/personal-follows.html?uid=1fn2gn0&acm=3.mce.1_10_1m5do.139413.0.uXJuTsJEPd0Y5.pos_9903-m_516674-sd_119",
                    "widgetId": 102,
                    "needExpose": true,
                    "iconUrl": "https://s10.mogucdn.com/mlcdn/c45406/190815_0k9k5gh362a1kbk87hha8ff1bek69_75x75.png",
                    "title": "关注",
                    "subTitle": ""
                }
            ],
            "title": "",
            "subTitle": "",
            "showHeader": false,
            "jumpUrl": "",
            "widgetType": "1"
        },
        {
            "widgetType": "2",
            "layoutType": "1",
            "itemListInfo": [
                {
                    "widgetId": 200,
                    "needExpose": true,
                    "iconUrl": "https://s10.mogucdn.com/mlcdn/c45406/190815_3637hh8ac09e50j7f07i7eealck4i_513x360.png",
                    "title": "购物车",
                    "subTitle": "",
                    "jumpUrl": "http://h5.mogu.com/cart/index.html?acm=3.mce.1_10_1m5ds.139413.0.uXJuTsJEPd0Y6.pos_9904-m_516676-sd_119"
                },
                {
                    "iconUrl": "",
                    "title": "卡券红包",
                    "subTitle": "6张活动券",
                    "jumpUrl": "http://h5.mogu.com/coupon/coupon/index.html?acm=3.mce.1_10_1m5du.139413.0.uXJuTsJEPd0Y7.pos_9905-m_516677-sd_119",
                    "widgetId": 201,
                    "needExpose": true
                },
                {
                    "iconUrl": "",
                    "title": "补贴保障",
                    "subTitle": "退货补运费",
                    "jumpUrl": "https://h5.mogu.com/insurance-shop/user-lite.html?acm=3.mce.1_10_1m5dy.139413.0.uXJuTsJEPd0Y8.pos_9906-m_516679-sd_119",
                    "widgetId": 202,
                    "needExpose": true
                },
                {
                    "widgetId": 203,
                    "needExpose": true,
                    "iconUrl": "",
                    "title": "我的钱包",
                    "subTitle": "白付美在这",
                    "jumpUrl": "https://act.mogu.com/walleth5full?acm=3.mce.1_10_1m5e0.139413.0.uXJuTsJEPd0Y9.pos_9907-m_516680-sd_119"
                }
            ],
            "title": "",
            "subTitle": "",
            "showHeader": false,
            "jumpUrl": ""
        },
        {
            "layoutType": "0",
            "itemListInfo": [
                {
                    "widgetId": 300,
                    "needExpose": true,
                    "iconUrl": "https://s10.mogucdn.com/mlcdn/c45406/190815_0ig16599k9l4f80g59cbkc6bcadid_75x75.png",
                    "title": "待付款",
                    "subTitle": "",
                    "jumpUrl": "https://h5.mogu.com/order/list.html?orderStatus=created&acm=3.mce.1_10_1m5e2.139413.0.uXJuTsJEPd0Ya.pos_9908-m_516681-sd_119"
                },
                {
                    "iconUrl": "https://s10.mogucdn.com/mlcdn/c45406/190815_5j02c44liecec503kdldjbh72hca8_75x75.png",
                    "title": "待发货",
                    "subTitle": "",
                    "jumpUrl": "https://h5.mogu.com/order/list.html?orderStatus=unshipped&acm=3.mce.1_10_1m86q.139413.0.uXJuTsJEPd0Yi.pos_9916-m_518493-sd_119",
                    "widgetId": 301,
                    "needExpose": true
                },
                {
                    "iconUrl": "https://s10.mogucdn.com/mlcdn/c45406/190815_56bd5eg3f4h47g2l1042436dc2950_75x75.png",
                    "title": "待收货",
                    "subTitle": "",
                    "jumpUrl": "https://h5.mogu.com/order/list.html?orderStatus=unreceived&acm=3.mce.1_10_1m5e6.139413.0.uXJuTsJEPd0Yb.pos_9909-m_516683-sd_119",
                    "widgetId": 302,
                    "needExpose": true
                },
                {
                    "iconUrl": "https://s10.mogucdn.com/mlcdn/c45406/190815_8af1b27cfaed15fllab4j3hffh7h8_75x75.png",
                    "title": "评价",
                    "subTitle": "",
                    "jumpUrl": "https://h5.mogu.com/order/list.html?type=rateCenter&acm=3.mce.1_10_1m5e8.139413.0.uXJuTsJEPd0Yc.pos_9910-m_516684-sd_119",
                    "widgetId": 303,
                    "needExpose": true
                },
                {
                    "jumpUrl": "https://h5.mogu.com/order/list.html?orderStatus=refund_orders&acm=3.mce.1_10_1m5ea.139413.0.uXJuTsJEPd0Yd.pos_9911-m_516685-sd_119",
                    "widgetId": 304,
                    "needExpose": true,
                    "iconUrl": "https://s10.mogucdn.com/mlcdn/c45406/190815_18db4je44bd6ej8ajg0l1950ia5ih_75x75.png",
                    "title": "退款售后",
                    "subTitle": ""
                }
            ],
            "title": "我的订单",
            "subTitle": "全部",
            "showHeader": true,
            "jumpUrl": "http://h5.mogu.com/order/list.html?acm=3.mce.1_10_1m5ts.139515.0.5KcpksJEPd0S2.pos_9902-m_516964-sd_119",
            "widgetType": "3"
        },
        {
            "showHeader": true,
            "jumpUrl": "",
            "widgetType": "4",
            "layoutType": "0",
            "itemListInfo": [
                {
                    "needExpose": true,
                    "iconUrl": "https://s10.mogucdn.com/mlcdn/c45406/190815_6f13a0l26fcfcgkhei88f8248024k_75x75.png",
                    "title": "签到",
                    "subTitle": "",
                    "jumpUrl": "https://act.mogu.com/qiandao?acm=3.mce.1_10_1m5ec.139413.0.uXJuTsJEPd0Ye.pos_9912-m_516686-sd_119",
                    "widgetId": 400
                },
                {
                    "widgetId": 401,
                    "needExpose": true,
                    "iconUrl": "https://s10.mogucdn.com/mlcdn/c45406/190815_8444j6413ccf1b00hb923a7l491ad_75x75.png",
                    "title": "大姨妈",
                    "subTitle": "",
                    "jumpUrl": "https://h5.mogu.com/period/schedule.html?acm=3.mce.1_10_1m5ee.139413.0.uXJuTsJEPd0Yf.pos_9913-m_516687-sd_119"
                },
                {
                    "subTitle": "",
                    "jumpUrl": "https://www.mogu.com/x/im?imver=1.2&show_header=qq#chat/b14ejg#23&acm=3.mce.1_10_1m5eg.139413.0.uXJuTsJEPd0Yg.pos_9914-m_516688-sd_119",
                    "widgetId": 402,
                    "needExpose": true,
                    "iconUrl": "https://s10.mogucdn.com/mlcdn/c45406/190815_54cd4b12ef09174hf1jkblbi69i2c_75x75.png",
                    "title": "客服"
                },
                {
                    "subTitle": "",
                    "jumpUrl": "https://h5.mogu.com/mogu-star/index.html?x_fullscreen=true&x_hide_navbar=true&acm=3.mce.1_10_1m5ei.139413.0.uXJuTsJEPd0Yh.pos_9915-m_516689-sd_119",
                    "widgetId": 403,
                    "needExpose": true,
                    "iconUrl": "https://s10.mogucdn.com/mlcdn/c45406/190815_10lcah52ick650jc36hgg2kafkj5f_75x75.png",
                    "title": "达人中心"
                }
            ],
            "title": "我的设置",
            "subTitle": ""
        }
    ]
}